stabbie/__init__.py
stabbie/stabbie.py
stabbie/fstab/__init__.py
stabbie/fstab/fstab.py
stabbie/fstab/entry/__init__.py
stabbie/fstab/entry/fstab_entry.py
stabbie/fstab/entry/fstab_entry_builder.py
stabbie/fstab/entry/mount_point.py
stabbie/fstab/entry/nfs_fstab_entry.py
stabbie/fstab/entry/remote_fstab_entry.py
stabbie/fstab/entry/service.py
stabbie/logging/__init__.py
stabbie/logging/color_log_formatter.py
stabbie-1.0.3.dist-info/LICENSE
stabbie-1.0.3.dist-info/METADATA
stabbie-1.0.3.dist-info/WHEEL
stabbie-1.0.3.dist-info/entry_points.txt
stabbie-1.0.3.dist-info/top_level.txt
stabbie-1.0.3.dist-info/RECORD
