Metadata-Version: 2.1
Name: stabbie
Version: 1.0.3
Summary: A friendly fstab auto-mount script for remote filesystems
License: GPLv3
Project-URL: Homepage, https://github.com/GeoffreyCoulaud/stabbie
Project-URL: Repository, https://github.com/GeoffreyCoulaud/stabbie.git
Keywords: fstab,mounting,linux,network share,nfs
Classifier: License :: OSI Approved :: GNU General Public License v3 (GPLv3)
Classifier: Programming Language :: Python :: 3.11
Classifier: Programming Language :: Python :: 3
Classifier: Operating System :: POSIX :: Linux
Classifier: Topic :: System :: Filesystems
Requires-Python: >=3.11
License-File: LICENSE
